setup.py
distributions_2020/Binomialdistribution.py
distributions_2020/Gaussiandistribution.py
distributions_2020/Generaldistribution.py
distributions_2020/__init__.py
distributions_2020.egg-info/PKG-INFO
distributions_2020.egg-info/SOURCES.txt
distributions_2020.egg-info/dependency_links.txt
distributions_2020.egg-info/not-zip-safe
distributions_2020.egg-info/top_level.txt