Metadata-Version: 1.0
Name: distributions-2020
Version: 1.0
Summary: Gaussian and Binomial distributions_2020
Home-page: UNKNOWN
Author: Ajmal Muhammed
Author-email: ajmalmohammedn@gmail.com
License: UNKNOWN
Platform: UNKNOWN
